paniki/__init__.py
paniki/py.typed
paniki/adapters/__init__.py
paniki/adapters/base_llm_adapter.py
paniki/adapters/schemas/__init__.py
paniki/adapters/schemas/function_schema.py
paniki/adapters/schemas/tools_schema.py
paniki/adapters/services/__init__.py
paniki/adapters/services/anthropic_adapter.py
paniki/adapters/services/gemini_adapter.py
paniki/adapters/services/open_ai_adapter.py
paniki/adapters/services/open_ai_realtime_adapter.py
paniki/audio/__init__.py
paniki/audio/utils.py
paniki/audio/filters/__init__.py
paniki/audio/filters/base_audio_filter.py
paniki/audio/filters/koala_filter.py
paniki/audio/filters/krisp_filter.py
paniki/audio/filters/noisereduce_filter.py
paniki/audio/mixers/__init__.py
paniki/audio/mixers/base_audio_mixer.py
paniki/audio/mixers/soundfile_mixer.py
paniki/audio/resamplers/__init__.py
paniki/audio/resamplers/base_audio_resampler.py
paniki/audio/resamplers/resampy_resampler.py
paniki/audio/resamplers/soxr_resampler.py
paniki/audio/turn/__init__.py
paniki/audio/turn/base_turn_analyzer.py
paniki/audio/turn/smart_turn/__init__.py
paniki/audio/turn/smart_turn/base_smart_turn.py
paniki/audio/turn/smart_turn/fal_smart_turn.py
paniki/audio/turn/smart_turn/http_smart_turn.py
paniki/audio/turn/smart_turn/local_coreml_smart_turn.py
paniki/audio/vad/__init__.py
paniki/audio/vad/silero.py
paniki/audio/vad/vad_analyzer.py
paniki/audio/vad/data/__init__.py
paniki/audio/vad/data/silero_vad.onnx
paniki/clocks/__init__.py
paniki/clocks/base_clock.py
paniki/clocks/system_clock.py
paniki/frames/__init__.py
paniki/frames/frames.proto
paniki/frames/frames.py
paniki/frames/protobufs/frames_pb2.py
paniki/metrics/__init__.py
paniki/metrics/metrics.py
paniki/observers/__init__.py
paniki/observers/base_observer.py
paniki/observers/loggers/__init__.py
paniki/observers/loggers/llm_log_observer.py
paniki/observers/loggers/transcription_log_observer.py
paniki/pipeline/__init__.py
paniki/pipeline/base_pipeline.py
paniki/pipeline/base_task.py
paniki_voice-0.1.dev25.dist-info/licenses/LICENSE
paniki_voice-0.1.dev25.dist-info/METADATA
paniki_voice-0.1.dev25.dist-info/WHEEL
paniki_voice-0.1.dev25.dist-info/top_level.txt
paniki_voice-0.1.dev25.dist-info/RECORD
